Covid19Dashboard_ah1062/config.json
Covid19Dashboard_ah1062/covid_data_handler.py
Covid19Dashboard_ah1062/covid_news_handling.py
Covid19Dashboard_ah1062/dashboard.py
Covid19Dashboard_ah1062/test_covid_data_handler.py
Covid19Dashboard_ah1062/test_dashboard.py
Covid19Dashboard_ah1062/test_news_data_handling.py
Covid19Dashboard_ah1062/CSV Data Files/nation_2021-10-28.csv
Covid19Dashboard_ah1062/templates/index.html
Covid19Dashboard_ah1062/templates/index_files/%20image.htm
Covid19Dashboard_ah1062/templates/index_files/bootstrap.css
Covid19Dashboard_ah1062/templates/index_files/bootstrap.js
Covid19Dashboard_ah1062/templates/index_files/jquery-3.js
Covid19Dashboard_ah1062/templates/index_files/popper.js
Covid19Dashboard_ah1062-0.0.13.dist-info/LICENSE
Covid19Dashboard_ah1062-0.0.13.dist-info/METADATA
Covid19Dashboard_ah1062-0.0.13.dist-info/WHEEL
Covid19Dashboard_ah1062-0.0.13.dist-info/top_level.txt
Covid19Dashboard_ah1062-0.0.13.dist-info/RECORD
