Metadata-Version: 2.1
Name: Covid19Dashboard-ah1062
Version: 0.0.13
Summary: Covid-19 Data Presentation Dashboard, ECM1400 Programming Coursework
Home-page: https://github.com/ah1062/Covid19Dashboard
Author: Alex Houghton
Author-email: ah1062@exeter.ac.uk
License: UNKNOWN
Platform: UNKNOWN
Requires-Python: >=3.9
